{
    "id": 112,
    "title": "Dalam Hening, Suara Batin Berbicara",
    "author": "Rachmat Maulana; Dr. Rachmat Maulana, S.Sos. M.Si; DWIMULYA PUSTAKA, Oktober, 2025; Rachmat Maulana,, lahir di Jakarta, 24 Oktober 1970, sebagai anak kelima; . Dari lurah, camat",
    "pretty_url": "belajar-menyadari-suara-batin",
    "price_new": "Rp99.000",
    "price_old": "Rp118.800",
    "discount": "20%",
    "image": "dalam-hening-suara-batin-berbicara.jpg",
    "description": "Buku \"BELAJAR MENYADARI SUARA BATIN\" - Publikasi terbaru dari Dwimulya Pustaka.",
    "publisher": "oleh",
    "isbn": "-",
    "language": "Indonesia",
    "publication_date": "7 Maret 2026",
    "pages": 145,
    "dimensions": "15,5 x 24 cm",
    "weight": "0.40 kg",
    "cover": "Soft Cover",
    "is_featured": false,
    "featured_order": null,
    "is_stacked": false,
    "stacked_priority": null
}