{
    "id": 129,
    "title": "Pengantar Ekonomi Makro",
    "author": "Dr. Rachmat Maulana, M.Si.; Fadjar Muliawan, S.E., M.M.; Miftahul Ulum, S.Kom., S.M., M.M.",
    "pretty_url": "pengantar-ekonomi-makro",
    "price_new": "Rp99.000",
    "price_old": "Rp118.800",
    "discount": "20%",
    "image": "pengantar-ekonomi-makro.jpg",
    "description": "Buku \"Pengantar Ekonomi Makro\" ini menghadirkan pemahaman komprehensif tentang teori, analisis, kebijakan, dan perspektif kontemporer dalam ekonomi makro yang relevan dengan dinamika perekonomian modern. Buku ini mengupas tuntas konsep-konsep fundamental seperti pendapatan nasional, inflasi, pengangguran, pertumbuhan ekonomi, hingga kebijakan fiskal dan moneter yang diterapkan oleh pemerintah dan bank sentral. Pembaca akan diajak memahami bagaimana variabel-variabel makroekonomi saling berinteraksi dan mempengaruhi kinerja perekonomian suatu negara, serta implikasinya terhadap dunia bisnis dan kehidupan masyarakat. Dilengkapi dengan studi kasus aktual dan data perekonomian Indonesia, buku ini memberikan wawasan tentang tantangan ekonomi global, krisis finansial, dan strategi pemulihan ekonomi. Sebuah referensi ideal bagi mahasiswa ekonomi, praktisi bisnis, dan siapa saja yang ingin memahami gambaran besar perekonomian serta kebijakan yang mempengaruhinya.",
    "publisher": "Penerbit Dwimulya Pustaka",
    "isbn": "-",
    "language": "Indonesia",
    "publication_date": "7 Maret 2026",
    "pages": 190,
    "dimensions": "15,5 x 24 cm",
    "weight": "0.40 kg",
    "cover": "Soft Cover",
    "is_featured": false,
    "featured_order": null,
    "is_stacked": false,
    "stacked_priority": null
}